octoflatbuffers/__init__.py
octoflatbuffers/_version.py
octoflatbuffers/builder.py
octoflatbuffers/compat.py
octoflatbuffers/encode.py
octoflatbuffers/flexbuffers.py
octoflatbuffers/number_types.py
octoflatbuffers/packer.py
octoflatbuffers/table.py
octoflatbuffers/util.py
octoflatbuffers-24.3.27.dist-info/METADATA
octoflatbuffers-24.3.27.dist-info/WHEEL
octoflatbuffers-24.3.27.dist-info/top_level.txt
octoflatbuffers-24.3.27.dist-info/RECORD
