Metadata-Version: 2.1
Name: octoflatbuffers
Version: 24.3.27
Summary: A fork of flatbuffers used for OctoEverywhere and Homeway
Home-page: https://github.com/QuinnDamerell/octoflatbuffers
Author: Quinn Damerell
Author-email: support@octoeverywhere.com
License: Apache 2.0
Project-URL: Documentation, https://github.com/QuinnDamerell/octoflatbuffers
Project-URL: Source, https://github.com/QuinnDamerell/octoflatbuffers
Project-URL: OctoEverywhere, https://octoeverywhere.com/?source=pypi
Project-URL: Homeway, https://homeway.io/?source=pypi
Classifier: Intended Audience :: Developers
Classifier: License :: OSI Approved :: Apache Software License
Classifier: Operating System :: OS Independent
Classifier: Programming Language :: Python
Classifier: Programming Language :: Python :: 2
Classifier: Programming Language :: Python :: 3
Classifier: Topic :: Software Development :: Libraries :: Python Modules
License-File: ../license
